peopleai_api/__init__.py
peopleai_api-0.0.4.dist-info/LICENSE
peopleai_api-0.0.4.dist-info/METADATA
peopleai_api-0.0.4.dist-info/WHEEL
peopleai_api-0.0.4.dist-info/top_level.txt
peopleai_api-0.0.4.dist-info/RECORD
