Metadata-Version: 2.1
Name: peopleai-api
Version: 0.0.4
Summary: Python library to download activities from People.ai's REST API
Home-page: https://github.com/maxzheng/peopleai-api
Author: Max Zheng
Author-email: maxzheng.os@gmail.com
License: MIT
Keywords: People.ai activities API
Platform: UNKNOWN
Classifier: Development Status :: 5 - Production/Stable
Classifier: Intended Audience :: Developers
Classifier: Topic :: Software Development :: Libraries
Classifier: License :: OSI Approved :: MIT License
Classifier: Programming Language :: Python :: 3
Classifier: Programming Language :: Python :: 3.6
Requires-Python: >=3.6
Requires-Dist: requests (==2.24.0)
